dogecoinrpc/__init__.py
dogecoinrpc/config.py
dogecoinrpc/connection.py
dogecoinrpc/data.py
dogecoinrpc/exceptions.py
dogecoinrpc/proxy.py
dogecoinrpc/util.py
python_dogecoin-0.2.0.dist-info/METADATA
python_dogecoin-0.2.0.dist-info/WHEEL
python_dogecoin-0.2.0.dist-info/RECORD
