Metadata-Version: 2.3
Name: python-dogecoin
Version: 0.2.0
Summary: Friendly Dogecoin JSON-RPC API binding for Python 3
License: MIT
Keywords: rpc,doge,dogecoin,blockchain,cryptocurrency,json-rpc,api,python-dogecoin
Author: Misha Behersky
Author-email: bmwant@gmail.com
Requires-Python: >=3.9
Classifier: Development Status :: 4 - Beta
Classifier: Environment :: Console
Classifier: Environment :: Web Environment
Classifier: Intended Audience :: Developers
Classifier: License :: OSI Approved :: MIT License
Classifier: Programming Language :: Python
Classifier: Programming Language :: Python :: 3
Classifier: Programming Language :: Python :: 3 :: Only
Classifier: Programming Language :: Python :: 3.9
Classifier: Programming Language :: Python :: 3.10
Classifier: Programming Language :: Python :: 3.11
Classifier: Programming Language :: Python :: 3.12
Classifier: Programming Language :: Python :: 3.13
Classifier: Topic :: Office/Business :: Financial
Provides-Extra: dev
Provides-Extra: docs
Requires-Dist: mkdocs (>=1.6.1,<2.0.0) ; extra == "docs"
Requires-Dist: mkdocstrings (>=0.29.1,<0.30.0) ; extra == "docs"
Requires-Dist: mkdocstrings-python[docs] (>=1.16.12,<2.0.0) ; extra == "docs"
Requires-Dist: pytest (>=8.4.0,<9.0.0) ; extra == "dev"
Requires-Dist: ruff (>=0.11.13,<0.12.0) ; extra == "dev"
